codegaze/__init__.py
codegaze/cli.py
codegaze/codegen.py
codegaze/codeparser.py
codegaze/datamodel.py
codegaze/datasets.py
codegaze/eval.py
codegaze/experiment.py
codegaze/metrics.py
codegaze/utils.py
codegaze/version.py
codegaze/web/__init__.py
codegaze/web/backend/__init__.py
codegaze/web/backend/app.py
codegaze/web/frontend/.env.default
codegaze/web/frontend/.gitignore
codegaze/web/frontend/README.md
codegaze/web/frontend/gatsby-browser.js
codegaze/web/frontend/gatsby-config.ts
codegaze/web/frontend/package.json
codegaze/web/frontend/postcss.config.js
codegaze/web/frontend/tailwind.config.js
codegaze/web/frontend/tsconfig.json
codegaze/web/frontend/yarn.lock
codegaze/web/frontend/node_modules/fmin/test.py
codegaze/web/frontend/src/components/atoms.tsx
codegaze/web/frontend/src/components/footer.tsx
codegaze/web/frontend/src/components/header.tsx
codegaze/web/frontend/src/components/icons.tsx
codegaze/web/frontend/src/components/layout.tsx
codegaze/web/frontend/src/components/login.tsx
codegaze/web/frontend/src/components/search.tsx
codegaze/web/frontend/src/components/utils.ts
codegaze/web/frontend/src/components/views/datasets.tsx
codegaze/web/frontend/src/components/views/dataexplorer/codeblock.tsx
codegaze/web/frontend/src/components/views/dataexplorer/dataexplorer.tsx
codegaze/web/frontend/src/components/views/dataexplorer/dataselector.tsx
codegaze/web/frontend/src/components/views/dataexplorer/index.tsx
codegaze/web/frontend/src/components/views/experiments/experiments.tsx
codegaze/web/frontend/src/components/views/experiments/heatmap.tsx
codegaze/web/frontend/src/components/views/experiments/metricselector.tsx
codegaze/web/frontend/src/components/views/experiments/modelcards.tsx
codegaze/web/frontend/src/components/views/experiments/modelselector.tsx
codegaze/web/frontend/src/components/views/experiments/results.tsx
codegaze/web/frontend/src/components/views/experiments/sankey.tsx
codegaze/web/frontend/src/hooks/provider.tsx
codegaze-0.0.23a0.dist-info/LICENSE
codegaze-0.0.23a0.dist-info/METADATA
codegaze-0.0.23a0.dist-info/WHEEL
codegaze-0.0.23a0.dist-info/entry_points.txt
codegaze-0.0.23a0.dist-info/top_level.txt
codegaze-0.0.23a0.dist-info/RECORD
