Metadata-Version: 2.1
Name: codegaze
Version: 0.0.23a0
Summary: Debug code generation models
Author-email: Victor Dibia <victor.dibia@gmail.com>
License: MIT License        
Project-URL: Homepage, https://github.com/victordibia/codegaze
Project-URL: Bug Tracker, https://github.com/victordibia/codegaze/issues
Classifier: Programming Language :: Python :: 3
Classifier: License :: OSI Approved :: MIT License
Classifier: Operating System :: OS Independent
Requires-Python: >=3.7
License-File: LICENSE
Requires-Dist: evaluate (~=0.1.2)
Requires-Dist: fastapi (~=0.78.0)
Requires-Dist: openai (~=0.20.0)
Requires-Dist: transformers (~=4.21.1)
Requires-Dist: tree-sitter (~=0.20.0)
Requires-Dist: typer (~=0.5.0)
Requires-Dist: Levenshtein
Requires-Dist: torch
Requires-Dist: torchvision
Requires-Dist: datasets
Requires-Dist: pydantic
Requires-Dist: uvicorn
